scholarag/__init__.py
scholarag/ds_utils.py
scholarag/generative_question_answering.py
scholarag/retrieve_metadata.py
scholarag/utils.py
scholarag/app/__init__.py
scholarag/app/config.py
scholarag/app/dependencies.py
scholarag/app/main.py
scholarag/app/middleware.py
scholarag/app/schemas.py
scholarag/app/streaming.py
scholarag/app/routers/__init__.py
scholarag/app/routers/qa.py
scholarag/app/routers/retrieval.py
scholarag/app/routers/suggestions.py
scholarag/document_stores/__init__.py
scholarag/document_stores/base.py
scholarag/document_stores/elastic.py
scholarag/document_stores/open.py
scholarag/scripts/__init__.py
scholarag/scripts/create_impact_factor_index.py
scholarag/scripts/manage_index.py
scholarag/scripts/parse_and_upload.py
scholarag/scripts/pmc_parse_and_upload.py
scholarag/scripts/pu_consumer.py
scholarag/scripts/pu_producer.py
scholarag/scripts/scholarag_api.py
scholarag/services/__init__.py
scholarag/services/cohere_reranker.py
scholarag/services/etl.py
scholarag/services/retrieval.py
scholarag-0.0.8.dist-info/AUTHORS.txt
scholarag-0.0.8.dist-info/LICENSE.md
scholarag-0.0.8.dist-info/METADATA
scholarag-0.0.8.dist-info/WHEEL
scholarag-0.0.8.dist-info/entry_points.txt
scholarag-0.0.8.dist-info/top_level.txt
scholarag-0.0.8.dist-info/RECORD
