Metadata-Version: 2.1
Name: scholarag
Version: 0.0.8
Summary: Pipelines for RAG on scientific papers
Author: Blue Brain Project, EPFL
Requires-Python: >=3.10
License-File: LICENSE.md
License-File: AUTHORS.txt
Requires-Dist: aiobotocore
Requires-Dist: asgi-correlation-id
Requires-Dist: boto3
Requires-Dist: cohere
Requires-Dist: elasticsearch>=8.5
Requires-Dist: elasticsearch-dsl
Requires-Dist: fastapi<=0.112.0
Requires-Dist: fastapi-pagination
Requires-Dist: httpx
Requires-Dist: python-dotenv
Requires-Dist: openai
Requires-Dist: openpyxl
Requires-Dist: opensearch-py>=2.5.0
Requires-Dist: pandas
Requires-Dist: pydantic
Requires-Dist: pydantic-settings
Requires-Dist: redis
Requires-Dist: sentry-sdk[fastapi]
Requires-Dist: types-redis
Requires-Dist: uvicorn
Provides-Extra: dev
Requires-Dist: bandit[toml]; extra == "dev"
Requires-Dist: moto[server]; extra == "dev"
Requires-Dist: mypy; extra == "dev"
Requires-Dist: pytest; extra == "dev"
Requires-Dist: pytest-cov; extra == "dev"
Requires-Dist: pytest_asyncio; extra == "dev"
Requires-Dist: pytest_httpx; extra == "dev"
Requires-Dist: ruff; extra == "dev"
Requires-Dist: types-requests; extra == "dev"
Provides-Extra: doc
Requires-Dist: mkdocs; extra == "doc"
Requires-Dist: mkdocs-material; extra == "doc"
Requires-Dist: mkdocstrings[python]; extra == "doc"
